swaggery-1.0.0a1.dist-info/top_level.txt
swaggery-1.0.0a1.dist-info/metadata.json
swaggery-1.0.0a1.dist-info/RECORD
swaggery-1.0.0a1.dist-info/WHEEL
swaggery-1.0.0a1.dist-info/DESCRIPTION.rst
swaggery-1.0.0a1.dist-info/METADATA
swaggery/application.py
swaggery/appinit.py
swaggery/logger.py
swaggery/utils.py
swaggery/checker.py
swaggery/responses.py
swaggery/__init__.py
swaggery/models.py
swaggery/api.py
swaggery/flowcontrol.py
swaggery/keywords.py
swaggery/testlib.py
swaggery/introspection/introspection.py
swaggery/introspection/resource-listing.json
swaggery/introspection/__init__.py
swaggery/introspection/api-declaration-schema.json
swaggery/introspection/test/__init__.py
swaggery/introspection/test/test_introspection.py
swaggery/test/test_responses.py
swaggery/test/test_application.py
swaggery/test/test_checker.py
swaggery/test/troubles.py
swaggery/test/test_flowcontrol.py
swaggery/test/__init__.py
swaggery/test/test_api.py
swaggery/test/dummymodule.py
swaggery/test/test_utils.py
swaggery/test/test_models.py
swaggery/test/test_testlib.py
swaggery/templates/swaggery.ini
swaggery/static/favicon.ico
swaggery-1.0.0a1.data/data/swaggery-examples/calc/calc.py
swaggery-1.0.0a1.data/data/swaggery-examples/async/async.py
swaggery-1.0.0a1.data/data/swaggery-examples/vetinari/vetinari.py
