Metadata-Version: 2.0
Name: swaggery
Version: 1.0.0a1
Summary: A Python3 framework to create self-documenting swagger APIs
Home-page: https://github.com/quasipedia/swaggery
Author: Mac Ryan
Author-email: quasipedia@gmail.com
License: AGPLv3+
Keywords: swagger API documentation asyncronous framework uWSGI WSGI
Platform: UNKNOWN
Classifier: License :: OSI Approved :: GNU Affero General Public License v3 or later (AGPLv3+)
Classifier: Development Status :: 3 - Alpha
Classifier: Intended Audience :: Developers
Classifier: Topic :: Software Development :: Build Tools
Classifier: Topic :: Documentation
Classifier: Topic :: Internet :: WWW/HTTP :: WSGI :: Application
Classifier: Topic :: Software Development :: Documentation
Classifier: Topic :: Software Development :: Libraries :: Application Frameworks
Classifier: Programming Language :: Python :: 3.3
Classifier: Programming Language :: Python :: 3.4
Requires-Dist: uWSGI (==2.0.7)
Requires-Dist: Werkzeug (==0.9.6)
Requires-Dist: jsonschema (==2.4.0)
Requires-Dist: docopt (==0.6.2)
Provides-Extra: dev
Requires-Dist: wheel (==0.24.0); extra == 'dev'
Requires-Dist: pip (==1.5.6); extra == 'dev'
Requires-Dist: twine (==1.3.1); extra == 'dev'
Provides-Extra: test
Requires-Dist: coverage (==3.7.1); extra == 'test'
Requires-Dist: nose (==1.3.4); extra == 'test'
Requires-Dist: rednose (==0.4.1); extra == 'test'
